{
  "db_name": "MySQL",
  "query": "SELECT DISTINCT d.container_name AS \"name!\"\n               FROM deployment_volumes dv\n               JOIN deployments d ON d.id = dv.deployment_id\n               WHERE dv.server_volume_id = ?\n                 AND d.container_name IS NOT NULL\n                 AND d.state IN ('PENDING','VALIDATING','PULLING_IMAGE','CREATING_CONTAINER',\n                                 'STARTING','RUNNING','STOPPING','STOPPED','RESTARTING',\n                                 'REMOVING','FAILED')",
  "describe": {
    "columns": [
      {
        "ordinal": 0,
        "name": "name!",
        "type_info": {
          "type": "VarString",
          "flags": "",
          "max_size": 1020
        }
      }
    ],
    "parameters": {
      "Right": 1
    },
    "nullable": [
      true
    ]
  },
  "hash": "780cc0516fa30912da77d9bc5a3ca4ab1acd15efc1829d7af7395005fa1dd13e"
}
