{
  "db_name": "MySQL",
  "query": "SELECT COUNT(*) FROM gitlab_projects WHERE gitlab_instance_id = ?",
  "describe": {
    "columns": [
      {
        "ordinal": 0,
        "name": "COUNT(*)",
        "type_info": {
          "type": "LongLong",
          "flags": "NOT_NULL | BINARY",
          "max_size": 21
        }
      }
    ],
    "parameters": {
      "Right": 1
    },
    "nullable": [
      false
    ]
  },
  "hash": "1dac97d08866219daa48299506102ac9e9df45f01b42ae704fd47832029a9145"
}
