{
  "db_name": "MySQL",
  "query": "SELECT id AS \"id: Uuid\", name FROM servers WHERE hostname = ? FOR UPDATE",
  "describe": {
    "columns": [
      {
        "ordinal": 0,
        "name": "id: Uuid",
        "type_info": {
          "type": "String",
          "flags": "NOT_NULL | PRIMARY_KEY | BINARY | NO_DEFAULT_VALUE",
          "max_size": 16
        }
      },
      {
        "ordinal": 1,
        "name": "name",
        "type_info": {
          "type": "VarString",
          "flags": "NOT_NULL | UNIQUE_KEY | NO_DEFAULT_VALUE",
          "max_size": 1020
        }
      }
    ],
    "parameters": {
      "Right": 1
    },
    "nullable": [
      false,
      false
    ]
  },
  "hash": "56519312f382e6723b99f49344e34fbb7dc33e0b7553625c9a1f4471f798cad9"
}
